systemdream-0.0.2.dist-info/top_level.txt
systemdream-0.0.2.dist-info/METADATA
systemdream-0.0.2.dist-info/metadata.json
systemdream-0.0.2.dist-info/WHEEL
systemdream-0.0.2.dist-info/RECORD
systemdream-0.0.2.dist-info/entry_points.txt
systemdream-0.0.2.dist-info/DESCRIPTION.rst
systemdream/__main__.py
systemdream/__init__.py
systemdream/journal/utils.py
systemdream/journal/reader.py
systemdream/journal/helpers.py
systemdream/journal/__init__.py
systemdream/journal/handler.py
